ObsiPy/__init__.py
ObsiPy/parser.py
obsipy-1.0.0.post1.dist-info/LICENSE
obsipy-1.0.0.post1.dist-info/METADATA
obsipy-1.0.0.post1.dist-info/WHEEL
obsipy-1.0.0.post1.dist-info/entry_points.txt
obsipy-1.0.0.post1.dist-info/RECORD
